MANIFEST.in
README.rst
setup.py
versiontools_support.py
skl_groups/__init__.py
skl_groups/features.py
skl_groups/preprocessing.py
skl_groups/utils.py
skl_groups.egg-info/PKG-INFO
skl_groups.egg-info/SOURCES.txt
skl_groups.egg-info/dependency_links.txt
skl_groups.egg-info/not-zip-safe
skl_groups.egg-info/pbr.json
skl_groups.egg-info/requires.txt
skl_groups.egg-info/top_level.txt
skl_groups/divergences/__init__.py
skl_groups/divergences/_knn.py
skl_groups/divergences/knn.py
skl_groups/kernels/__init__.py
skl_groups/kernels/mmk.py
skl_groups/kernels/transform.py
skl_groups/summaries/__init__.py
skl_groups/summaries/bag_of_words.py
skl_groups/summaries/l2_density.py
skl_groups/summaries/mean.py
skl_groups/tests/__init__.py
skl_groups/tests/test_divs_knn.py
skl_groups/tests/test_features.py
skl_groups/tests/test_mmk.py
skl_groups/tests/test_preprocessing.py
skl_groups/tests/test_summaries.py
skl_groups/tests/test_transforms.py
skl_groups/tests/test_utils.py